LICENSE
MANIFEST.in
README.rst
requirements.txt
setup.py
sulu.py
docs/override.txt-sample
sulu.egg-info/PKG-INFO
sulu.egg-info/SOURCES.txt
sulu.egg-info/dependency_links.txt
sulu.egg-info/entry_points.txt
sulu.egg-info/requires.txt
sulu.egg-info/top_level.txt