Metadata-Version: 1.1
Name: sulu
Version: 0.1.20150805
Summary: Sign update.rdf of mozilla add-ons in Python
Home-page: https://github.com/l-hedgehog/sulu
Author: Hector Zhao
Author-email: bzhao@mozilla.com
License: MPL 2.0
Platform: UNKNOWN
Classifier: Development Status :: 4 - Beta
Classifier: Environment :: Console
Classifier: Intended Audience :: Developers
Classifier: License :: OSI Approved :: Mozilla Public License 2.0 (MPL 2.0)
Classifier: Operating System :: OS Independent
Classifier: Programming Language :: Python
Requires: lxml
Requires: M2Crypto
Requires: pyasn1
Requires: rdflib (==3.1.0)
Provides: sulu
